soupsavvy/VERSION
soupsavvy/__init__.py
soupsavvy/api.py
soupsavvy/base.py
soupsavvy/exceptions.py
soupsavvy/interfaces.py
soupsavvy/operators.py
soupsavvy/implementation/__init__.py
soupsavvy/implementation/bs4.py
soupsavvy/implementation/element.py
soupsavvy/implementation/lxml.py
soupsavvy/implementation/playwright.py
soupsavvy/implementation/selenium.py
soupsavvy/models/__init__.py
soupsavvy/models/base.py
soupsavvy/models/constants.py
soupsavvy/models/wrappers.py
soupsavvy/operations/__init__.py
soupsavvy/operations/conditional.py
soupsavvy/operations/element.py
soupsavvy/operations/general.py
soupsavvy/operations/selection_pipeline.py
soupsavvy/operations/wrappers.py
soupsavvy/selectors/__init__.py
soupsavvy/selectors/attributes.py
soupsavvy/selectors/combinators.py
soupsavvy/selectors/general.py
soupsavvy/selectors/logical.py
soupsavvy/selectors/namespace.py
soupsavvy/selectors/relative.py
soupsavvy/selectors/css/__init__.py
soupsavvy/selectors/css/api.py
soupsavvy/selectors/css/selectors.py
soupsavvy/selectors/nth/__init__.py
soupsavvy/selectors/nth/nth_utils.py
soupsavvy/selectors/nth/selectors.py
soupsavvy/selectors/xpath/__init__.py
soupsavvy/selectors/xpath/api.py
soupsavvy/selectors/xpath/selectors.py
soupsavvy/testing/__init__.py
soupsavvy/testing/generators/__init__.py
soupsavvy/testing/generators/base.py
soupsavvy/testing/generators/generators.py
soupsavvy/testing/generators/namespace.py
soupsavvy/testing/generators/templates/__init__.py
soupsavvy/testing/generators/templates/base.py
soupsavvy/testing/generators/templates/config.py
soupsavvy/testing/generators/templates/templates.py
soupsavvy/utils/__init__.py
soupsavvy/utils/logging.py
soupsavvy/utils/selector_utils.py
soupsavvy-1.0.1.dist-info/licenses/LICENSE
soupsavvy-1.0.1.dist-info/METADATA
soupsavvy-1.0.1.dist-info/WHEEL
soupsavvy-1.0.1.dist-info/top_level.txt
soupsavvy-1.0.1.dist-info/RECORD
