Metadata-Version: 2.4
Name: soupsavvy
Version: 1.0.1
Summary: Powerful and flexible search engine for BeautifulSoup
Author: sewcio543
License: MIT License
Project-URL: Repository, https://github.com/sewcio543/soupsavvy
Project-URL: Homepage, https://soupsavvy.readthedocs.io
Keywords: web-scraping,html,soup,bs4,markup,beautifulsoup,css
Classifier: Development Status :: 3 - Alpha
Classifier: Intended Audience :: Developers
Classifier: License :: OSI Approved :: MIT License
Classifier: Operating System :: OS Independent
Classifier: Programming Language :: Python :: 3
Classifier: Programming Language :: Python :: 3.9
Classifier: Programming Language :: Python :: 3.10
Classifier: Programming Language :: Python :: 3.11
Classifier: Programming Language :: Python :: 3.12
Classifier: Programming Language :: Python :: 3.13
Requires-Python: >=3.9
License-File: LICENSE
Requires-Dist: typing_extensions>=4.6.1
Provides-Extra: lxml
Requires-Dist: lxml; extra == "lxml"
Requires-Dist: cssselect; extra == "lxml"
Provides-Extra: bs4
Requires-Dist: beautifulsoup4; extra == "bs4"
Requires-Dist: soupsieve; extra == "bs4"
Provides-Extra: selenium
Requires-Dist: selenium; extra == "selenium"
Dynamic: license-file
